{
  "locations": [
    {
      "label": "서울특별시",
      "value": "seoul",
      "children": [
        {
          "label": "강남구",
          "value": "gangnam",
          "children": [
            { "label": "역삼동", "value": "yeoksam" },
            { "label": "개포동", "value": "gaepo" },
            { "label": "압구정동", "value": "apgujeong" },
            { "label": "청담동", "value": "cheongdam" },
            { "label": "삼성동", "value": "samsung" },
            { "label": "논현동", "value": "nonhyeon" }
          ]
        },
        {
          "label": "강서구",
          "value": "gangseo",
          "children": [
            { "label": "화곡동", "value": "hwagok" },
            { "label": "등촌동", "value": "deungchon" },
            { "label": "염창동", "value": "yeomchang" },
            { "label": "발산동", "value": "balsan" },
            { "label": "마곡동", "value": "magok" }
          ]
        },
        {
          "label": "종로구",
          "value": "jongno",
          "children": [
            { "label": "명동", "value": "myeongdong" },
            { "label": "인사동", "value": "insadong" },
            { "label": "종로1가", "value": "jongno1ga" },
            { "label": "종로3가", "value": "jongno3ga" },
            { "label": "종로5가", "value": "jongno5ga" }
          ]
        },
        {
          "label": "강동구",
          "value": "gangdong",
          "children": [
            { "label": "천호동", "value": "cheonho" },
            { "label": "둔촌동", "value": "dunchon" },
            { "label": "암사동", "value": "amsa" },
            { "label": "강일동", "value": "gangil" }
          ]
        },
        {
          "label": "관악구",
          "value": "gwanak",
          "children": [
            { "label": "신림동", "value": "sillim" },
            { "label": "봉천동", "value": "bongcheon" },
            { "label": "관악동", "value": "gwanakdong" }
          ]
        },
        {
          "label": "광진구",
          "value": "gwangjin",
          "children": [
            { "label": "건대입구", "value": "konkuk" },
            { "label": "화양동", "value": "hwayang" },
            { "label": "자양동", "value": "jayang" }
          ]
        },
        {
          "label": "서초구",
          "value": "seocho",
          "children": [
            { "label": "서초동", "value": "seochodynamic" },
            { "label": "반포동", "value": "banpo" },
            { "label": "잠원동", "value": "jamwon" },
            { "label": "방배동", "value": "bangbae" }
          ]
        },
        {
          "label": "마포구",
          "value": "mapo",
          "children": [
            { "label": "홍대입구", "value": "hongik" },
            { "label": "합정동", "value": "hapjeong" },
            { "label": "상암동", "value": "sangam" },
            { "label": "연남동", "value": "yeonnam" }
          ]
        }
      ]
    },
    {
      "label": "경기도",
      "value": "gyeonggi",
      "children": [
        {
          "label": "성남시",
          "value": "seongnam",
          "children": [
            { "label": "분당구", "value": "bundang" },
            { "label": "수정구", "value": "sujeong" },
            { "label": "중원구", "value": "jungwon" },
            { "label": "판교동", "value": "pangyo" },
            { "label": "정자동", "value": "jeongja" }
          ]
        },
        {
          "label": "수원시",
          "value": "suwon",
          "children": [
            { "label": "영통구", "value": "yeongtong" },
            { "label": "팔달구", "value": "paldal" },
            { "label": "권선구", "value": "gwonseon" },
            { "label": "장안구", "value": "jangan" }
          ]
        },
        {
          "label": "고양시",
          "value": "goyang",
          "children": [
            { "label": "일산동구", "value": "ilsandong" },
            { "label": "일산서구", "value": "ilsanseo" },
            { "label": "덕양구", "value": "deokyang" }
          ]
        },
        {
          "label": "안양시",
          "value": "anyang",
          "children": [
            { "label": "만안구", "value": "manan" },
            { "label": "동안구", "value": "dongan" }
          ]
        },
        {
          "label": "부천시",
          "value": "bucheon",
          "children": [
            { "label": "원미구", "value": "wonmi" },
            { "label": "소사구", "value": "sosa" },
            { "label": "오정구", "value": "ojeong" }
          ]
        }
      ]
    },
    {
      "label": "부산광역시",
      "value": "busan",
      "children": [
        {
          "label": "해운대구",
          "value": "haeundae",
          "children": [
            { "label": "해운대동", "value": "haeundaedong" },
            { "label": "좌동", "value": "jwadong" },
            { "label": "우동", "value": "udong" },
            { "label": "중동", "value": "jungdong" },
            { "label": "송정동", "value": "songjeong" }
          ]
        },
        {
          "label": "부산진구",
          "value": "busanjin",
          "children": [
            { "label": "서면", "value": "seomyeon" },
            { "label": "부전동", "value": "bujeondong" },
            { "label": "전포동", "value": "jeonpodong" },
            { "label": "양정동", "value": "yangjeong" }
          ]
        },
        {
          "label": "동래구",
          "value": "dongnae",
          "children": [
            { "label": "동래동", "value": "dongnaedong" },
            { "label": "온천동", "value": "oncheon" },
            { "label": "사직동", "value": "sajik" }
          ]
        }
      ]
    },
    {
      "label": "인천광역시",
      "value": "incheon",
      "children": [
        {
          "label": "남동구",
          "value": "namdong",
          "children": [
            { "label": "구월동", "value": "guwol" },
            { "label": "간석동", "value": "ganseok" },
            { "label": "만수동", "value": "mansu" }
          ]
        },
        {
          "label": "연수구",
          "value": "yeonsu",
          "children": [
            { "label": "송도동", "value": "songdo" },
            { "label": "연수동", "value": "yeonsudong" },
            { "label": "청학동", "value": "cheonghak" }
          ]
        }
      ]
    },
    {
      "label": "대구광역시",
      "value": "daegu",
      "children": [
        {
          "label": "중구",
          "value": "jung",
          "children": [
            { "label": "동성로", "value": "dongseongro" },
            { "label": "대신동", "value": "daesin" },
            { "label": "남산동", "value": "namsan" }
          ]
        },
        {
          "label": "수성구",
          "value": "suseong",
          "children": [
            { "label": "범어동", "value": "beomeo" },
            { "label": "수성동", "value": "suseongdong" },
            { "label": "황금동", "value": "hwanggeum" }
          ]
        }
      ]
    }
  ],
  "categories": [
    {
      "label": "외식/음료",
      "value": "food",
      "children": [
        { "label": "카페/디저트", "value": "cafe" },
        { "label": "패스트푸드", "value": "fastfood" },
        { "label": "한식당", "value": "korean" },
        { "label": "중식당", "value": "chinese" },
        { "label": "일식당", "value": "japanese" },
        { "label": "양식당", "value": "western" },
        { "label": "치킨/피자", "value": "chicken_pizza" },
        { "label": "펜션/민박", "value": "pension" },
        { "label": "바/호프", "value": "bar" },
        { "label": "베이커리", "value": "bakery" }
      ]
    },
    {
      "label": "판매/영업",
      "value": "sales",
      "children": [
        { "label": "매장관리", "value": "store" },
        { "label": "영업/마케팅", "value": "marketing" },
        { "label": "판매원", "value": "salesperson" },
        { "label": "계산원", "value": "cashier" },
        { "label": "상품관리", "value": "product_management" },
        { "label": "고객상담", "value": "customer_service" },
        { "label": "텔레마케팅", "value": "telemarketing" },
        { "label": "온라인쇼핑몰", "value": "online_mall" }
      ]
    },
    {
      "label": "사무직",
      "value": "office",
      "children": [
        { "label": "일반사무", "value": "general_office" },
        { "label": "경리/회계", "value": "accounting" },
        { "label": "인사/총무", "value": "hr_affairs" },
        { "label": "기획/전략", "value": "planning" },
        { "label": "데이터입력", "value": "data_entry" },
        { "label": "문서작성", "value": "documentation" },
        { "label": "번역/통역", "value": "translation" },
        { "label": "비서", "value": "secretary" }
      ]
    },
    {
      "label": "IT/개발",
      "value": "it",
      "children": [
        { "label": "웹개발", "value": "web_dev" },
        { "label": "앱개발", "value": "app_dev" },
        { "label": "UI/UX디자인", "value": "ui_ux" },
        { "label": "웹디자인", "value": "web_design" },
        { "label": "퍼블리셔", "value": "publisher" },
        { "label": "데이터분석", "value": "data_analysis" },
        { "label": "네트워크관리", "value": "network" },
        { "label": "시스템관리", "value": "system_admin" },
        { "label": "QA/테스터", "value": "qa_tester" }
      ]
    },
    {
      "label": "서비스업",
      "value": "service",
      "children": [
        { "label": "청소/정리", "value": "cleaning" },
        { "label": "배달/운송", "value": "delivery" },
        { "label": "주차관리", "value": "parking" },
        { "label": "경비/보안", "value": "security" },
        { "label": "펜션관리", "value": "pension_manage" },
        { "label": "미용/헤어", "value": "beauty_hair" },
        { "label": "네일/속눈썹", "value": "nail_lash" },
        { "label": "마사지/스파", "value": "massage_spa" },
        { "label": "반려동물관리", "value": "pet_care" }
      ]
    },
    {
      "label": "교육/강사",
      "value": "education",
      "children": [
        { "label": "학원강사", "value": "academy" },
        { "label": "과외/개인교습", "value": "tutoring" },
        { "label": "유치원/어린이집", "value": "kindergarten" },
        { "label": "영어강사", "value": "english_teacher" },
        { "label": "수학강사", "value": "math_teacher" },
        { "label": "예체능강사", "value": "art_sports" },
        { "label": "온라인강의", "value": "online_lecture" },
        { "label": "교육컨설팅", "value": "edu_consulting" }
      ]
    },
    {
      "label": "생산/제조",
      "value": "manufacturing",
      "children": [
        { "label": "조립/포장", "value": "assembly_packing" },
        { "label": "품질관리", "value": "quality_control" },
        { "label": "기계조작", "value": "machine_operation" },
        { "label": "용접/절단", "value": "welding_cutting" },
        { "label": "도장/표면처리", "value": "painting_surface" },
        { "label": "전자부품", "value": "electronics" },
        { "label": "자동차부품", "value": "auto_parts" },
        { "label": "화학/제약", "value": "chemical_pharma" }
      ]
    },
    {
      "label": "건설/건축",
      "value": "construction",
      "children": [
        { "label": "건설현장", "value": "construction_site" },
        { "label": "인테리어", "value": "interior" },
        { "label": "페인트/도배", "value": "paint_wallpaper" },
        { "label": "타일/바닥재", "value": "tile_flooring" },
        { "label": "전기/설비", "value": "electrical_facility" },
        { "label": "배관/보일러", "value": "plumbing_boiler" },
        { "label": "조경/원예", "value": "landscaping" },
        { "label": "철거/해체", "value": "demolition" }
      ]
    },
    {
      "label": "의료/간병",
      "value": "medical",
      "children": [
        { "label": "간병인", "value": "caregiver" },
        { "label": "요양보호사", "value": "care_worker" },
        { "label": "의료진", "value": "medical_staff" },
        { "label": "약국", "value": "pharmacy" },
        { "label": "치과", "value": "dental" },
        { "label": "한의원", "value": "oriental_clinic" },
        { "label": "동물병원", "value": "vet_clinic" },
        { "label": "의료기기", "value": "medical_device" }
      ]
    }
  ]
}
